tidal2tidal/__init__.py
tidal2tidal/__main__.py
tidal2tidal/tidal2tidal.py
tidal2tidal-0.0.0.1.dist-info/LICENSE
tidal2tidal-0.0.0.1.dist-info/METADATA
tidal2tidal-0.0.0.1.dist-info/WHEEL
tidal2tidal-0.0.0.1.dist-info/entry_points.txt
tidal2tidal-0.0.0.1.dist-info/top_level.txt
tidal2tidal-0.0.0.1.dist-info/RECORD
