Metadata-Version: 2.1
Name: tidal2tidal
Version: 0.0.0.1
Summary: A command line tool for transferring liked tracks, albums, artists and playlists between Tidal accounts.
Author-email: Victor Cabre <victorcabreg@gmail.com>
Project-URL: Homepage, https://github.com/victorcabre/tidal2tidal
Project-URL: Issues, https://github.com/victorcabre/tidal2tidal/issues
Classifier: Programming Language :: Python :: 3
Classifier: License :: OSI Approved :: MIT License
Classifier: Operating System :: OS Independent
Requires-Python: >=3.8
License-File: LICENSE
Requires-Dist: tidalapi
Requires-Dist: tqdm
